[
	{"drawDate": "08-01-2024", "one" : "30*16", "two" : "17*21", "three" : "12*10"},
	{"drawDate": "08-02-2024", "one" : "04*36", "two" : "26*19", "three" : "02*19"},
	{"drawDate": "08-03-2024", "one" : "31*23", "two" : "07*34", "three" : "30*29"},
	{"drawDate": "08-04-2024", "one" : "11*17", "two" : "34*32", "three" : "21*31"},
	{"drawDate": "08-05-2024", "one" : "18*04", "two" : "03*17", "three" : "37*33"},
	{"drawDate": "08-06-2024", "one" : "05*26", "two" : "06*23", "three" : "30*30"},
	{"drawDate": "08-07-2024", "one" : "28*36", "two" : "36*18", "three" : "14*15"},
	{"drawDate": "08-08-2024", "one" : "24*04", "two" : "18*24", "three" : "30*36"},
	{"drawDate": "08-09-2024", "one" : "26*27", "two" : "32*15", "three" : "27*25"},
	{"drawDate": "08-10-2024", "one" : "32*22", "two" : "35*15", "three" : "34*19"},
	{"drawDate": "08-11-2024", "one" : "32*30", "two" : "07*30", "three" : "14*22"},
	{"drawDate": "08-12-2024", "one" : "33*13", "two" : "14*32", "three" : "13*13"},
	{"drawDate": "08-13-2024", "one" : "27*29", "two" : "08*36", "three" : "36*18"},
	{"drawDate": "08-14-2024", "one" : "19*09", "two" : "05*11", "three" : "17*27"},
	{"drawDate": "08-15-2024", "one" : "05*14", "two" : "25*38", "three" : "34*09"},
	{"drawDate": "08-16-2024", "one" : "31*05", "two" : "19*05", "three" : "14*24"},
	{"drawDate": "08-17-2024", "one" : "12*18", "two" : "", "three" : ""}
]
